branca/__init__.py
branca/_cnames.json
branca/_schemes.json
branca/_version.py
branca/colormap.py
branca/element.py
branca/scheme_base_codes.json
branca/scheme_info.json
branca/utilities.py
branca/templates/color_scale.js
branca-0.8.0.dist-info/LICENSE.txt
branca-0.8.0.dist-info/METADATA
branca-0.8.0.dist-info/WHEEL
branca-0.8.0.dist-info/top_level.txt
branca-0.8.0.dist-info/RECORD
