Metadata-Version: 2.1
Name: branca
Version: 0.8.0
Summary: Generate complex HTML+JS pages with Python
Home-page: https://github.com/python-visualization/branca
Author: Martin Journois
License: MIT
Keywords: data visualization
Classifier: Programming Language :: Python :: 3
Classifier: Programming Language :: Python :: 3.8
Classifier: Programming Language :: Python :: 3.9
Classifier: Programming Language :: Python :: 3.10
Classifier: Programming Language :: Python :: 3.11
Classifier: Programming Language :: Python :: 3.12
Classifier: License :: OSI Approved :: MIT License
Classifier: Development Status :: 5 - Production/Stable
Requires-Python: >=3.7
License-File: LICENSE.txt
Requires-Dist: jinja2>=3
